stresst/__init__.py
stresst/strs.py
stresst-0.2.0.dist-info/LICENSE.txt
stresst-0.2.0.dist-info/METADATA
stresst-0.2.0.dist-info/WHEEL
stresst-0.2.0.dist-info/entry_points.txt
stresst-0.2.0.dist-info/top_level.txt
stresst-0.2.0.dist-info/RECORD
